{ "backgroundcolor":"#646464",
 "height":40,
 "hexsidelength":25,
 "infinite":false,
 "layers":[
        {
         "data":[0, 0, 0, 0, 0, 0, 0, 0, 0, 0, 0, 0, 0, 0, 0, 0, 0, 0, 0, 0, 0, 0, 0, 0, 0, 0, 0, 0, 0, 0, 0, 0, 0, 0, 0, 0, 0, 0, 0, 0, 0, 0, 0, 0, 0, 0, 0, 0, 0, 0, 0, 0, 0, 0, 0, 0, 0, 0, 0, 0, 0, 0, 0, 0, 0, 0, 0, 0, 0, 0, 0, 0, 0, 0, 0, 0, 0, 0, 0, 0, 0, 0, 0, 0, 0, 0, 0, 0, 0, 0, 0, 0, 0, 0, 0, 0, 0, 0, 0, 0, 0, 0, 0, 0, 0, 0, 0, 0, 0, 0, 0, 0, 0, 0, 0, 0, 0, 0, 0, 0, 0, 0, 0, 0, 0, 0, 0, 0, 0, 0, 0, 0, 0, 0, 0, 0, 0, 0, 0, 0, 0, 0, 0, 0, 0, 0, 0, 0, 0, 0, 0, 0, 0, 0, 0, 0, 0, 0, 0, 0, 0, 0, 0, 0, 0, 0, 0, 0, 0, 0, 0, 0, 0, 0, 0, 0, 0, 0, 0, 0, 0, 0, 0, 0, 0, 0, 0, 0, 0, 0, 0, 0, 0, 0, 0, 0, 0, 0, 0, 0, 0, 0, 0, 0, 0, 0, 0, 0, 0, 0, 0, 0, 0, 0, 0, 0, 0, 0, 0, 0, 0, 0, 0, 0, 0, 0, 0, 0, 0, 0, 0, 0, 0, 0, 0, 0, 0, 0, 0, 0, 0, 0, 0, 0, 0, 0, 0, 0, 0, 0, 0, 0, 0, 0, 0, 0, 0, 0, 0, 0, 0, 0, 0, 0, 0, 0, 0, 0, 0, 0, 0, 0, 0, 0, 0, 0, 0, 0, 0, 0, 0, 0, 0, 0, 0, 0, 0, 0, 0, 0, 0, 0, 0, 0, 0, 0, 0, 0, 0, 0, 0, 0, 0, 0, 0, 0, 0, 0, 0, 0, 0, 0, 0, 0, 0, 0, 0, 0, 0, 0, 0, 0, 0, 0, 0, 0, 0, 0, 0, 0, 0, 0, 0, 0, 0, 0, 0, 0, 0, 0, 0, 0, 0, 0, 0, 0, 0, 0, 0, 0, 0, 0, 0, 0, 0, 0, 0, 0, 0, 0, 0, 0, 0, 0, 0, 0, 0, 0, 0, 0, 0, 0, 0, 0, 0, 0, 0, 0, 0, 0, 0, 0, 0, 0, 0, 0, 0, 0, 0, 0, 0, 0, 0, 0, 0, 0, 0, 0, 0, 0, 0, 0, 0, 0, 0, 0, 0, 0, 0, 0, 0, 0, 0, 0, 0, 0, 0, 0, 0, 0, 0, 0, 0, 0, 0, 0, 0, 0, 0, 0, 0, 0, 0, 0, 0, 0, 0, 0, 0, 0, 0, 0, 0, 0, 0, 0, 0, 0, 0, 0, 0, 0, 0, 0, 0, 5, 5, 5, 5, 5, 5, 5, 5, 5, 0, 0, 0, 0, 0, 0, 0, 0, 0, 0, 0, 0, 0, 0, 0, 0, 0, 0, 0, 0, 0, 0, 0, 0, 0, 0, 0, 0, 0, 0, 0, 5, 7, 7, 7, 2, 2, 2, 2, 2, 5, 0, 0, 0, 0, 0, 0, 0, 0, 0, 0, 0, 0, 0, 0, 0, 0, 0, 0, 0, 0, 0, 0, 0, 0, 0, 0, 0, 0, 0, 5, 7, 7, 7, 2, 2, 2, 3, 2, 2, 5, 0, 0, 0, 0, 0, 0, 0, 0, 0, 0, 0, 0, 0, 0, 0, 0, 0, 0, 0, 0, 0, 0, 0, 0, 0, 0, 0, 0, 0, 5, 2, 7, 7, 3, 3, 3, 3, 3, 3, 3, 5, 0, 0, 0, 0, 0, 0, 0, 0, 0, 0, 0, 0, 0, 0, 0, 0, 0, 0, 0, 0, 0, 0, 0, 0, 0, 0, 0, 5, 2, 2, 7, 3, 3, 3, 3, 2, 2, 3, 2, 5, 0, 0, 0, 0, 0, 0, 0, 0, 0, 0, 0, 0, 0, 0, 0, 0, 0, 0, 0, 0, 0, 0, 0, 0, 0, 0, 0, 5, 2, 5, 2, 3, 3, 3, 3, 6, 2, 2, 2, 1, 5, 0, 0, 0, 0, 0, 0, 0, 0, 0, 0, 0, 0, 0, 0, 0, 0, 0, 0, 0, 0, 0, 0, 0, 0, 0, 5, 5, 5, 5, 6, 6, 6, 6, 6, 3, 3, 2, 1, 1, 5, 0, 0, 0, 0, 0, 0, 0, 0, 0, 0, 0, 0, 0, 0, 0, 0, 0, 0, 0, 0, 0, 0, 0, 0, 0, 5, 5, 5, 5, 6, 6, 6, 6, 6, 6, 3, 2, 1, 1, 1, 5, 0, 0, 0, 0, 0, 0, 0, 0, 0, 0, 0, 0, 0, 0, 0, 0, 0, 0, 0, 0, 0, 0, 0, 5, 5, 8, 5, 2, 6, 6, 6, 7, 6, 3, 3, 2, 2, 1, 1, 5, 0, 0, 0, 0, 0, 0, 0, 0, 0, 0, 0, 0, 0, 0, 0, 0, 0, 0, 0, 0, 0, 0, 0, 0, 5, 8, 8, 8, 6, 6, 6, 6, 6, 3, 3, 2, 2, 1, 1, 5, 0, 0, 0, 0, 0, 0, 0, 0, 0, 0, 0, 0, 0, 0, 0, 0, 0, 0, 0, 0, 0, 0, 0, 0, 5, 8, 8, 8, 2, 6, 6, 2, 3, 3, 3, 2, 2, 1, 5, 0, 0, 0, 0, 0, 0, 0, 0, 0, 0, 0, 0, 0, 0, 0, 0, 0, 0, 0, 0, 0, 0, 0, 0, 0, 0, 5, 8, 8, 3, 3, 3, 3, 3, 3, 3, 8, 2, 1, 5, 0, 0, 0, 0, 0, 0, 0, 0, 0, 0, 0, 0, 0, 0, 0, 0, 0, 0, 0, 0, 0, 0, 0, 0, 0, 0, 5, 8, 3, 3, 3, 3, 3, 3, 3, 3, 8, 2, 5, 0, 0, 0, 0, 0, 0, 0, 0, 0, 0, 0, 0, 0, 0, 0, 0, 0, 0, 0, 0, 0, 0, 0, 0, 0, 0, 0, 0, 5, 8, 3, 3, 3, 3, 3, 8, 8, 8, 2, 5, 0, 0, 0, 0, 0, 0, 0, 0, 0, 0, 0, 0, 0, 0, 0, 0, 0, 0, 0, 0, 0, 0, 0, 0, 0, 0, 0, 0, 5, 8, 8, 8, 8, 8, 8, 2, 2, 2, 5, 0, 0, 0, 0, 0, 0, 0, 0, 0, 0, 0, 0, 0, 0, 0, 0, 0, 0, 0, 0, 0, 0, 0, 0, 0, 0, 0, 0, 0, 0, 5, 8, 8, 2, 2, 2, 2, 3, 3, 5, 0, 0, 0, 0, 0, 0, 0, 0, 0, 0, 0, 0, 0, 0, 0, 0, 0, 0, 0, 0, 0, 0, 0, 0, 0, 0, 0, 0, 0, 0, 5, 5, 5, 5, 5, 5, 5, 5, 5, 0, 0, 0, 0, 0, 0, 0, 0, 0, 0, 0, 0, 0, 0, 0, 0, 0, 0, 0, 0, 0, 0, 0, 0, 0, 0, 0, 0, 0, 0, 0, 0, 0, 0, 0, 0, 0, 0, 0, 0, 0, 0, 0, 0, 0, 0, 0, 0, 0, 0, 0, 0, 0, 0, 0, 0, 0, 0, 0, 0, 0, 0, 0, 0, 0, 0, 0, 0, 0, 0, 0, 0, 0, 0, 0, 0, 0, 0, 0, 0, 0, 0, 0, 0, 0, 0, 0, 0, 0, 0, 0, 0, 0, 0, 0, 0, 0, 0, 0, 0, 0, 0, 0, 0, 0, 0, 0, 0, 0, 0, 0, 0, 0, 0, 0, 0, 0, 0, 0, 0, 0, 0, 0, 0, 0, 0, 0, 0, 0, 0, 0, 0, 0, 0, 0, 0, 0, 0, 0, 0, 0, 0, 0, 0, 0, 0, 0, 0, 0, 0, 0, 0, 0, 0, 0, 0, 0, 0, 0, 0, 0, 0, 0, 0, 0, 0, 0, 0, 0, 0, 0, 0, 0, 0, 0, 0, 0, 0, 0, 0, 0, 0, 0, 0, 0, 0, 0, 0, 0, 0, 0, 0, 0, 0, 0, 0, 0, 0, 0, 0, 0, 0, 0, 0, 0, 0, 0, 0, 0, 0, 0, 0, 0, 0, 0, 0, 0, 0, 0, 0, 0, 0, 0, 0, 0, 0, 0, 0, 0, 0, 0, 0, 0, 0, 0, 0, 0, 0, 0, 0, 0, 0, 0, 0, 0, 0, 0, 0, 0, 0, 0, 0, 0, 0, 0, 0, 0, 0, 0, 0, 0, 0, 0, 0, 0, 0, 0, 0, 0, 0, 0, 0, 0, 0, 0, 0, 0, 0, 0, 0, 0, 0, 0, 0, 0, 0, 0, 0, 0, 0, 0, 0, 0, 0, 0, 0, 0, 0, 0, 0, 0, 0, 0, 0, 0, 0, 0, 0, 0, 0, 0, 0, 0, 0, 0, 0, 0, 0, 0, 0, 0, 0, 0, 0, 0, 0, 0, 0, 0, 0, 0, 0, 0, 0, 0, 0, 0, 0, 0, 0, 0, 0, 0, 0, 0, 0, 0, 0, 0, 0, 0, 0, 0, 0, 0, 0, 0, 0, 0, 0, 0, 0, 0, 0, 0, 0, 0, 0, 0, 0, 0, 0, 0, 0, 0, 0, 0, 0, 0, 0, 0, 0, 0, 0, 0, 0, 0, 0, 0, 0, 0, 0, 0, 0, 0, 0, 0, 0, 0, 0, 0, 0, 0, 0, 0, 0, 0, 0, 0, 0, 0, 0, 0, 0, 0, 0, 0, 0, 0, 0, 0, 0, 0, 0, 0, 0, 0, 0, 0, 0, 0, 0, 0, 0, 0, 0, 0, 0, 0, 0, 0, 0, 0, 0, 0, 0, 0, 0, 0, 0, 0, 0, 0, 0, 0, 0, 0, 0, 0, 0, 0, 0, 0, 0, 0, 0, 0, 0, 0, 0, 0, 0, 0, 0, 0, 0, 0, 0, 0, 0, 0, 0, 0, 0, 0, 0, 0, 0, 0, 0, 0, 0, 0, 0, 0, 0],
         "height":40,
         "id":1,
         "name":"hexes",
         "opacity":1,
         "type":"tilelayer",
         "visible":true,
         "width":40,
         "x":0,
         "y":0
        }, 
        {
         "draworder":"topdown",
         "id":3,
         "name":"decals",
         "objects":[
                {
                 "gid":11,
                 "height":11,
                 "id":18,
                 "name":"",
                 "rotation":0,
                 "type":"",
                 "visible":true,
                 "width":12,
                 "x":1038.76,
                 "y":642.97
                }, 
                {
                 "gid":11,
                 "height":11,
                 "id":19,
                 "name":"",
                 "rotation":0,
                 "type":"",
                 "visible":true,
                 "width":12,
                 "x":1103.14,
                 "y":644.433
                }, 
                {
                 "gid":11,
                 "height":11,
                 "id":23,
                 "name":"",
                 "rotation":0,
                 "type":"",
                 "visible":true,
                 "width":12,
                 "x":1073.15,
                 "y":610.051
                }, 
                {
                 "gid":11,
                 "height":11,
                 "id":24,
                 "name":"",
                 "rotation":0,
                 "type":"",
                 "visible":true,
                 "width":12,
                 "x":1152.88,
                 "y":589.568
                }, 
                {
                 "gid":11,
                 "height":11,
                 "id":25,
                 "name":"",
                 "rotation":0,
                 "type":"",
                 "visible":true,
                 "width":12,
                 "x":1134.6,
                 "y":610.051
                }, 
                {
                 "gid":11,
                 "height":11,
                 "id":26,
                 "name":"",
                 "rotation":0,
                 "type":"",
                 "visible":true,
                 "width":12,
                 "x":1110.45,
                 "y":579.327
                }, 
                {
                 "gid":11,
                 "height":11,
                 "id":27,
                 "name":"",
                 "rotation":0,
                 "type":"",
                 "visible":true,
                 "width":12,
                 "x":963.228,
                 "y":601.374
                }, 
                {
                 "gid":11,
                 "height":11,
                 "id":28,
                 "name":"",
                 "rotation":0,
                 "type":"",
                 "visible":true,
                 "width":12,
                 "x":1216.53,
                 "y":561.77
                }, 
                {
                 "gid":11,
                 "height":11,
                 "id":29,
                 "name":"",
                 "rotation":0,
                 "type":"",
                 "visible":true,
                 "width":12,
                 "x":1202,
                 "y":568.886
                }, 
                {
                 "gid":11,
                 "height":11,
                 "id":30,
                 "name":"",
                 "rotation":0,
                 "type":"",
                 "visible":true,
                 "width":12,
                 "x":1185,
                 "y":703.886
                }, 
                {
                 "gid":11,
                 "height":11,
                 "id":31,
                 "name":"",
                 "rotation":0,
                 "type":"",
                 "visible":true,
                 "width":12,
                 "x":1249.45,
                 "y":688.325
                }, 
                {
                 "gid":11,
                 "height":11,
                 "id":32,
                 "name":"",
                 "rotation":0,
                 "type":"",
                 "visible":true,
                 "width":12,
                 "x":1202,
                 "y":694.886
                }, 
                {
                 "gid":11,
                 "height":11,
                 "id":33,
                 "name":"",
                 "rotation":0,
                 "type":"",
                 "visible":true,
                 "width":12,
                 "x":1203,
                 "y":735.886
                }, 
                {
                 "gid":11,
                 "height":11,
                 "id":34,
                 "name":"",
                 "rotation":0,
                 "type":"",
                 "visible":true,
                 "width":12,
                 "x":1184.17,
                 "y":748.886
                }, 
                {
                 "gid":11,
                 "height":11,
                 "id":35,
                 "name":"",
                 "rotation":0,
                 "type":"",
                 "visible":true,
                 "width":12,
                 "x":1203.27,
                 "y":807.732
                }, 
                {
                 "gid":11,
                 "height":11,
                 "id":36,
                 "name":"",
                 "rotation":0,
                 "type":"",
                 "visible":true,
                 "width":12,
                 "x":1220.83,
                 "y":750.672
                }, 
                {
                 "gid":11,
                 "height":11,
                 "id":37,
                 "name":"",
                 "rotation":0,
                 "type":"",
                 "visible":true,
                 "width":12,
                 "x":1231.07,
                 "y":847.234
                }, 
                {
                 "gid":11,
                 "height":11,
                 "id":38,
                 "name":"",
                 "rotation":0,
                 "type":"",
                 "visible":true,
                 "width":12,
                 "x":1190.11,
                 "y":877.958
                }, 
                {
                 "gid":11,
                 "height":11,
                 "id":40,
                 "name":"",
                 "rotation":0,
                 "type":"",
                 "visible":true,
                 "width":12,
                 "x":1167.17,
                 "y":849.886
                }, 
                {
                 "gid":11,
                 "height":11,
                 "id":42,
                 "name":"",
                 "rotation":0,
                 "type":"",
                 "visible":true,
                 "width":12,
                 "x":1207.17,
                 "y":932.226
                }, 
                {
                 "gid":11,
                 "height":11,
                 "id":43,
                 "name":"",
                 "rotation":0,
                 "type":"",
                 "visible":true,
                 "width":12,
                 "x":1222.53,
                 "y":924.911
                }, 
                {
                 "gid":11,
                 "height":11,
                 "id":44,
                 "name":"",
                 "rotation":0,
                 "type":"",
                 "visible":true,
                 "width":12,
                 "x":1191.17,
                 "y":897.886
                }, 
                {
                 "gid":11,
                 "height":11,
                 "id":45,
                 "name":"",
                 "rotation":0,
                 "type":"",
                 "visible":true,
                 "width":12,
                 "x":1145.17,
                 "y":896.886
                }, 
                {
                 "gid":11,
                 "height":11,
                 "id":46,
                 "name":"",
                 "rotation":0,
                 "type":"",
                 "visible":true,
                 "width":12,
                 "x":1164.17,
                 "y":920.886
                }, 
                {
                 "gid":11,
                 "height":11,
                 "id":47,
                 "name":"",
                 "rotation":0,
                 "type":"",
                 "visible":true,
                 "width":12,
                 "x":1165.93,
                 "y":934.104
                }, 
                {
                 "gid":11,
                 "height":11,
                 "id":48,
                 "name":"",
                 "rotation":0,
                 "type":"",
                 "visible":true,
                 "width":12,
                 "x":1120.69,
                 "y":939.621
                }, 
                {
                 "gid":11,
                 "height":11,
                 "id":50,
                 "name":"",
                 "rotation":0,
                 "type":"",
                 "visible":true,
                 "width":12,
                 "x":1089.17,
                 "y":928.886
                }, 
                {
                 "gid":11,
                 "height":11,
                 "id":51,
                 "name":"",
                 "rotation":0,
                 "type":"",
                 "visible":true,
                 "width":12,
                 "x":1132.27,
                 "y":864.035
                }, 
                {
                 "gid":11,
                 "height":11,
                 "id":52,
                 "name":"",
                 "rotation":0,
                 "type":"",
                 "visible":true,
                 "width":12,
                 "x":1134.48,
                 "y":924.173
                }, 
                {
                 "gid":11,
                 "height":11,
                 "id":53,
                 "name":"",
                 "rotation":0,
                 "type":"",
                 "visible":true,
                 "width":12,
                 "x":1167.03,
                 "y":893.276
                }, 
                {
                 "gid":11,
                 "height":11,
                 "id":54,
                 "name":"",
                 "rotation":0,
                 "type":"",
                 "visible":true,
                 "width":12,
                 "x":1121.24,
                 "y":898.794
                }, 
                {
                 "gid":11,
                 "height":11,
                 "id":55,
                 "name":"",
                 "rotation":0,
                 "type":"",
                 "visible":true,
                 "width":12,
                 "x":1184.14,
                 "y":828.173
                }, 
                {
                 "gid":11,
                 "height":11,
                 "id":56,
                 "name":"",
                 "rotation":0,
                 "type":"",
                 "visible":true,
                 "width":12,
                 "x":1159.31,
                 "y":811.069
                }, 
                {
                 "gid":11,
                 "height":11,
                 "id":57,
                 "name":"",
                 "rotation":0,
                 "type":"",
                 "visible":true,
                 "width":12,
                 "x":881.103,
                 "y":886.886
                }, 
                {
                 "gid":11,
                 "height":11,
                 "id":58,
                 "name":"",
                 "rotation":0,
                 "type":"",
                 "visible":true,
                 "width":12,
                 "x":955,
                 "y":936
                }, 
                {
                 "gid":11,
                 "height":11,
                 "id":59,
                 "name":"",
                 "rotation":0,
                 "type":"",
                 "visible":true,
                 "width":12,
                 "x":924,
                 "y":934.886
                }, 
                {
                 "gid":11,
                 "height":11,
                 "id":60,
                 "name":"",
                 "rotation":0,
                 "type":"",
                 "visible":true,
                 "width":12,
                 "x":939,
                 "y":972
                }, 
                {
                 "gid":11,
                 "height":11,
                 "id":61,
                 "name":"",
                 "rotation":0,
                 "type":"",
                 "visible":true,
                 "width":12,
                 "x":978.345,
                 "y":969.127
                }, 
                {
                 "gid":11,
                 "height":11,
                 "id":62,
                 "name":"",
                 "rotation":0,
                 "type":"",
                 "visible":true,
                 "width":12,
                 "x":931,
                 "y":950.576
                }, 
                {
                 "gid":11,
                 "height":11,
                 "id":63,
                 "name":"",
                 "rotation":0,
                 "type":"",
                 "visible":true,
                 "width":12,
                 "x":982.034,
                 "y":934.61
                }, 
                {
                 "gid":11,
                 "height":11,
                 "id":66,
                 "name":"",
                 "rotation":0,
                 "type":"",
                 "visible":true,
                 "width":12,
                 "x":973,
                 "y":914
                }, 
                {
                 "gid":11,
                 "height":11,
                 "id":68,
                 "name":"",
                 "rotation":0,
                 "type":"",
                 "visible":true,
                 "width":12,
                 "x":993.069,
                 "y":917.507
                }, 
                {
                 "gid":11,
                 "height":11,
                 "id":69,
                 "name":"",
                 "rotation":0,
                 "type":"",
                 "visible":true,
                 "width":12,
                 "x":1215,
                 "y":1056.89
                }, 
                {
                 "gid":11,
                 "height":11,
                 "id":70,
                 "name":"",
                 "rotation":0,
                 "type":"",
                 "visible":true,
                 "width":12,
                 "x":1205,
                 "y":1047.72
                }, 
                {
                 "gid":11,
                 "height":11,
                 "id":71,
                 "name":"",
                 "rotation":0,
                 "type":"",
                 "visible":true,
                 "width":12,
                 "x":1239.21,
                 "y":1044.41
                }, 
                {
                 "gid":10,
                 "height":20,
                 "id":72,
                 "name":"",
                 "rotation":0,
                 "type":"",
                 "visible":true,
                 "width":15,
                 "x":1266.34,
                 "y":1046.65
                }, 
                {
                 "gid":10,
                 "height":20,
                 "id":73,
                 "name":"",
                 "rotation":0,
                 "type":"",
                 "visible":true,
                 "width":15,
                 "x":1221.66,
                 "y":1043.89
                }, 
                {
                 "gid":10,
                 "height":20,
                 "id":75,
                 "name":"",
                 "rotation":0,
                 "type":"",
                 "visible":true,
                 "width":15,
                 "x":1209.3,
                 "y":902.886
                }, 
                {
                 "gid":10,
                 "height":20,
                 "id":76,
                 "name":"",
                 "rotation":0,
                 "type":"",
                 "visible":true,
                 "width":15,
                 "x":1198.59,
                 "y":822.138
                }, 
                {
                 "gid":10,
                 "height":20,
                 "id":77,
                 "name":"",
                 "rotation":0,
                 "type":"",
                 "visible":true,
                 "width":15,
                 "x":1149.17,
                 "y":845.886
                }, 
                {
                 "gid":10,
                 "height":20,
                 "id":78,
                 "name":"",
                 "rotation":0,
                 "type":"",
                 "visible":true,
                 "width":15,
                 "x":1093.21,
                 "y":902.69
                }, 
                {
                 "gid":10,
                 "height":20,
                 "id":79,
                 "name":"",
                 "rotation":0,
                 "type":"",
                 "visible":true,
                 "width":15,
                 "x":1068.93,
                 "y":928.069
                }, 
                {
                 "gid":10,
                 "height":20,
                 "id":80,
                 "name":"",
                 "rotation":0,
                 "type":"",
                 "visible":true,
                 "width":15,
                 "x":1018.17,
                 "y":945.173
                }, 
                {
                 "gid":10,
                 "height":20,
                 "id":81,
                 "name":"",
                 "rotation":0,
                 "type":"",
                 "visible":true,
                 "width":15,
                 "x":1041,
                 "y":972.886
                }, 
                {
                 "gid":10,
                 "height":20,
                 "id":82,
                 "name":"",
                 "rotation":0,
                 "type":"",
                 "visible":true,
                 "width":15,
                 "x":953,
                 "y":963
                }, 
                {
                 "gid":10,
                 "height":20,
                 "id":83,
                 "name":"",
                 "rotation":0,
                 "type":"",
                 "visible":true,
                 "width":15,
                 "x":1215.17,
                 "y":764.886
                }, 
                {
                 "gid":10,
                 "height":20,
                 "id":84,
                 "name":"",
                 "rotation":0,
                 "type":"",
                 "visible":true,
                 "width":15,
                 "x":1175,
                 "y":769.886
                }, 
                {
                 "gid":10,
                 "height":20,
                 "id":85,
                 "name":"",
                 "rotation":0,
                 "type":"",
                 "visible":true,
                 "width":15,
                 "x":1185.9,
                 "y":784.069
                }, 
                {
                 "gid":10,
                 "height":20,
                 "id":86,
                 "name":"",
                 "rotation":0,
                 "type":"",
                 "visible":true,
                 "width":15,
                 "x":1230,
                 "y":707.886
                }, 
                {
                 "gid":10,
                 "height":20,
                 "id":87,
                 "name":"",
                 "rotation":0,
                 "type":"",
                 "visible":true,
                 "width":15,
                 "x":1310,
                 "y":584.886
                }, 
                {
                 "gid":10,
                 "height":20,
                 "id":88,
                 "name":"",
                 "rotation":0,
                 "type":"",
                 "visible":true,
                 "width":15,
                 "x":1289,
                 "y":576.886
                }, 
                {
                 "gid":10,
                 "height":20,
                 "id":89,
                 "name":"",
                 "rotation":0,
                 "type":"",
                 "visible":true,
                 "width":15,
                 "x":1303,
                 "y":602.886
                }, 
                {
                 "gid":10,
                 "height":20,
                 "id":90,
                 "name":"",
                 "rotation":0,
                 "type":"",
                 "visible":true,
                 "width":15,
                 "x":1311.86,
                 "y":559.828
                }, 
                {
                 "gid":10,
                 "height":20,
                 "id":91,
                 "name":"",
                 "rotation":0,
                 "type":"",
                 "visible":true,
                 "width":15,
                 "x":1270.48,
                 "y":575.828
                }, 
                {
                 "gid":10,
                 "height":20,
                 "id":92,
                 "name":"",
                 "rotation":0,
                 "type":"",
                 "visible":true,
                 "width":15,
                 "x":1237,
                 "y":575.886
                }, 
                {
                 "gid":10,
                 "height":20,
                 "id":93,
                 "name":"",
                 "rotation":0,
                 "type":"",
                 "visible":true,
                 "width":15,
                 "x":1191,
                 "y":545.886
                }, 
                {
                 "gid":10,
                 "height":20,
                 "id":94,
                 "name":"",
                 "rotation":0,
                 "type":"",
                 "visible":true,
                 "width":15,
                 "x":1109,
                 "y":616.886
                }, 
                {
                 "gid":10,
                 "height":20,
                 "id":95,
                 "name":"",
                 "rotation":0,
                 "type":"",
                 "visible":true,
                 "width":15,
                 "x":1163.45,
                 "y":570.311
                }, 
                {
                 "gid":10,
                 "height":20,
                 "id":96,
                 "name":"",
                 "rotation":0,
                 "type":"",
                 "visible":true,
                 "width":15,
                 "x":1073,
                 "y":629.886
                }, 
                {
                 "gid":10,
                 "height":20,
                 "id":97,
                 "name":"",
                 "rotation":0,
                 "type":"",
                 "visible":true,
                 "width":15,
                 "x":1050,
                 "y":590.886
                }, 
                {
                 "gid":10,
                 "height":20,
                 "id":98,
                 "name":"",
                 "rotation":0,
                 "type":"",
                 "visible":true,
                 "width":15,
                 "x":1036.55,
                 "y":612.794
                }, 
                {
                 "gid":10,
                 "height":20,
                 "id":99,
                 "name":"",
                 "rotation":0,
                 "type":"",
                 "visible":true,
                 "width":15,
                 "x":1007,
                 "y":655.886
                }, 
                {
                 "gid":10,
                 "height":20,
                 "id":100,
                 "name":"",
                 "rotation":0,
                 "type":"",
                 "visible":true,
                 "width":15,
                 "x":1014,
                 "y":628.886
                }, 
                {
                 "gid":10,
                 "height":20,
                 "id":101,
                 "name":"",
                 "rotation":0,
                 "type":"",
                 "visible":true,
                 "width":15,
                 "x":1039.14,
                 "y":903.794
                }, 
                {
                 "gid":10,
                 "height":20,
                 "id":102,
                 "name":"",
                 "rotation":0,
                 "type":"",
                 "visible":true,
                 "width":15,
                 "x":1039.17,
                 "y":933.886
                }, 
                {
                 "gid":16,
                 "height":66,
                 "id":103,
                 "name":"",
                 "rotation":0,
                 "type":"",
                 "visible":true,
                 "width":29,
                 "x":931,
                 "y":585
                }, 
                {
                 "gid":16,
                 "height":66,
                 "id":104,
                 "name":"",
                 "rotation":0,
                 "type":"",
                 "visible":true,
                 "width":29,
                 "x":875,
                 "y":586
                }, 
                {
                 "gid":17,
                 "height":66,
                 "id":105,
                 "name":"",
                 "rotation":0,
                 "type":"",
                 "visible":true,
                 "width":32,
                 "x":958,
                 "y":544
                }, 
                {
                 "gid":17,
                 "height":66,
                 "id":106,
                 "name":"",
                 "rotation":0,
                 "type":"",
                 "visible":true,
                 "width":32,
                 "x":983,
                 "y":507
                }, 
                {
                 "gid":15,
                 "height":66,
                 "id":107,
                 "name":"",
                 "rotation":0,
                 "type":"",
                 "visible":true,
                 "width":32,
                 "x":874,
                 "y":495.886
                }, 
                {
                 "gid":9,
                 "height":20,
                 "id":109,
                 "name":"",
                 "rotation":0,
                 "type":"",
                 "visible":true,
                 "width":15,
                 "x":1216,
                 "y":634.886
                }, 
                {
                 "gid":9,
                 "height":20,
                 "id":110,
                 "name":"",
                 "rotation":0,
                 "type":"",
                 "visible":true,
                 "width":15,
                 "x":1273,
                 "y":638.886
                }, 
                {
                 "gid":9,
                 "height":20,
                 "id":111,
                 "name":"",
                 "rotation":0,
                 "type":"",
                 "visible":true,
                 "width":15,
                 "x":1237.38,
                 "y":603.414
                }, 
                {
                 "gid":9,
                 "height":20,
                 "id":112,
                 "name":"",
                 "rotation":0,
                 "type":"",
                 "visible":true,
                 "width":15,
                 "x":1252.28,
                 "y":654.725
                }, 
                {
                 "gid":9,
                 "height":20,
                 "id":113,
                 "name":"",
                 "rotation":0,
                 "type":"",
                 "visible":true,
                 "width":15,
                 "x":1245,
                 "y":625.886
                }, 
                {
                 "gid":9,
                 "height":20,
                 "id":114,
                 "name":"",
                 "rotation":0,
                 "type":"",
                 "visible":true,
                 "width":15,
                 "x":1299.17,
                 "y":643.69
                }, 
                {
                 "gid":9,
                 "height":20,
                 "id":115,
                 "name":"",
                 "rotation":0,
                 "type":"",
                 "visible":true,
                 "width":15,
                 "x":1321,
                 "y":654.886
                }, 
                {
                 "gid":9,
                 "height":20,
                 "id":116,
                 "name":"",
                 "rotation":0,
                 "type":"",
                 "visible":true,
                 "width":15,
                 "x":1293,
                 "y":721.886
                }, 
                {
                 "gid":9,
                 "height":20,
                 "id":117,
                 "name":"",
                 "rotation":0,
                 "type":"",
                 "visible":true,
                 "width":15,
                 "x":1305,
                 "y":697.886
                }, 
                {
                 "gid":9,
                 "height":20,
                 "id":118,
                 "name":"",
                 "rotation":0,
                 "type":"",
                 "visible":true,
                 "width":15,
                 "x":1339.55,
                 "y":626.886
                }, 
                {
                 "gid":13,
                 "height":11,
                 "id":119,
                 "name":"",
                 "rotation":0,
                 "type":"",
                 "visible":true,
                 "width":12,
                 "x":866.931,
                 "y":848.714
                }, 
                {
                 "gid":13,
                 "height":11,
                 "id":120,
                 "name":"",
                 "rotation":0,
                 "type":"",
                 "visible":true,
                 "width":12,
                 "x":837.138,
                 "y":820.024
                }, 
                {
                 "gid":13,
                 "height":11,
                 "id":121,
                 "name":"",
                 "rotation":0,
                 "type":"",
                 "visible":true,
                 "width":12,
                 "x":816.724,
                 "y":843.196
                }, 
                {
                 "gid":13,
                 "height":11,
                 "id":122,
                 "name":"",
                 "rotation":0,
                 "type":"",
                 "visible":true,
                 "width":12,
                 "x":832.172,
                 "y":877.403
                }, 
                {
                 "gid":13,
                 "height":11,
                 "id":123,
                 "name":"",
                 "rotation":0,
                 "type":"",
                 "visible":true,
                 "width":12,
                 "x":777.552,
                 "y":807.886
                }, 
                {
                 "gid":13,
                 "height":11,
                 "id":124,
                 "name":"",
                 "rotation":0,
                 "type":"",
                 "visible":true,
                 "width":12,
                 "x":761,
                 "y":850.369
                }, 
                {
                 "gid":12,
                 "height":11,
                 "id":125,
                 "name":"",
                 "rotation":0,
                 "type":"",
                 "visible":true,
                 "width":12,
                 "x":1063,
                 "y":788.886
                }, 
                {
                 "gid":12,
                 "height":11,
                 "id":126,
                 "name":"",
                 "rotation":0,
                 "type":"",
                 "visible":true,
                 "width":12,
                 "x":1087,
                 "y":788.886
                }, 
                {
                 "gid":12,
                 "height":11,
                 "id":127,
                 "name":"",
                 "rotation":0,
                 "type":"",
                 "visible":true,
                 "width":12,
                 "x":1075,
                 "y":792.886
                }, 
                {
                 "gid":12,
                 "height":11,
                 "id":128,
                 "name":"",
                 "rotation":0,
                 "type":"",
                 "visible":true,
                 "width":12,
                 "x":1076,
                 "y":836.449
                }, 
                {
                 "gid":12,
                 "height":11,
                 "id":129,
                 "name":"",
                 "rotation":0,
                 "type":"",
                 "visible":true,
                 "width":12,
                 "x":1086.48,
                 "y":850.794
                }, 
                {
                 "gid":12,
                 "height":11,
                 "id":132,
                 "name":"",
                 "rotation":0,
                 "type":"",
                 "visible":true,
                 "width":12,
                 "x":1394.62,
                 "y":833.61
                }, 
                {
                 "gid":12,
                 "height":11,
                 "id":133,
                 "name":"",
                 "rotation":0,
                 "type":"",
                 "visible":true,
                 "width":12,
                 "x":1397.93,
                 "y":855.679
                }, 
                {
                 "gid":12,
                 "height":11,
                 "id":134,
                 "name":"",
                 "rotation":0,
                 "type":"",
                 "visible":true,
                 "width":12,
                 "x":1365.93,
                 "y":893.748
                }, 
                {
                 "gid":12,
                 "height":11,
                 "id":135,
                 "name":"",
                 "rotation":0,
                 "type":"",
                 "visible":true,
                 "width":12,
                 "x":1377.52,
                 "y":890.438
                }, 
                {
                 "gid":12,
                 "height":11,
                 "id":136,
                 "name":"",
                 "rotation":0,
                 "type":"",
                 "visible":true,
                 "width":12,
                 "x":1377,
                 "y":902.886
                }, 
                {
                 "gid":12,
                 "height":11,
                 "id":137,
                 "name":"",
                 "rotation":0,
                 "type":"",
                 "visible":true,
                 "width":12,
                 "x":1416.14,
                 "y":856.231
                }, 
                {
                 "gid":12,
                 "height":11,
                 "id":138,
                 "name":"",
                 "rotation":0,
                 "type":"",
                 "visible":true,
                 "width":12,
                 "x":1387.45,
                 "y":798.852
                }, 
                {
                 "gid":12,
                 "height":11,
                 "id":139,
                 "name":"",
                 "rotation":0,
                 "type":"",
                 "visible":true,
                 "width":12,
                 "x":1370.34,
                 "y":811.541
                }, 
                {
                 "gid":12,
                 "height":11,
                 "id":140,
                 "name":"",
                 "rotation":0,
                 "type":"",
                 "visible":true,
                 "width":12,
                 "x":1400.14,
                 "y":811.541
                }, 
                {
                 "gid":12,
                 "height":11,
                 "id":141,
                 "name":"",
                 "rotation":0,
                 "type":"",
                 "visible":true,
                 "width":12,
                 "x":1422.76,
                 "y":797.748
                }, 
                {
                 "gid":12,
                 "height":11,
                 "id":142,
                 "name":"",
                 "rotation":0,
                 "type":"",
                 "visible":true,
                 "width":12,
                 "x":1434.9,
                 "y":822.576
                }, 
                {
                 "gid":12,
                 "height":11,
                 "id":143,
                 "name":"",
                 "rotation":0,
                 "type":"",
                 "visible":true,
                 "width":12,
                 "x":1444.83,
                 "y":764.093
                }, 
                {
                 "gid":12,
                 "height":11,
                 "id":144,
                 "name":"",
                 "rotation":0,
                 "type":"",
                 "visible":true,
                 "width":12,
                 "x":1399.59,
                 "y":766.3
                }, 
                {
                 "gid":12,
                 "height":11,
                 "id":145,
                 "name":"",
                 "rotation":0,
                 "type":"",
                 "visible":true,
                 "width":12,
                 "x":1406.21,
                 "y":734.3
                }, 
                {
                 "gid":12,
                 "height":11,
                 "id":146,
                 "name":"",
                 "rotation":0,
                 "type":"",
                 "visible":true,
                 "width":12,
                 "x":1362.62,
                 "y":735.955
                }, 
                {
                 "gid":12,
                 "height":11,
                 "id":147,
                 "name":"",
                 "rotation":0,
                 "type":"",
                 "visible":true,
                 "width":12,
                 "x":1386,
                 "y":731.886
                }, 
                {
                 "gid":12,
                 "height":11,
                 "id":148,
                 "name":"",
                 "rotation":0,
                 "type":"",
                 "visible":true,
                 "width":12,
                 "x":1402,
                 "y":695.886
                }, 
                {
                 "gid":12,
                 "height":11,
                 "id":149,
                 "name":"",
                 "rotation":0,
                 "type":"",
                 "visible":true,
                 "width":12,
                 "x":1369,
                 "y":658.886
                }, 
                {
                 "gid":12,
                 "height":11,
                 "id":150,
                 "name":"",
                 "rotation":0,
                 "type":"",
                 "visible":true,
                 "width":12,
                 "x":1390.21,
                 "y":681.886
                }, 
                {
                 "gid":12,
                 "height":11,
                 "id":151,
                 "name":"",
                 "rotation":0,
                 "type":"",
                 "visible":true,
                 "width":12,
                 "x":1356,
                 "y":686.852
                }, 
                {
                 "gid":12,
                 "height":11,
                 "id":152,
                 "name":"",
                 "rotation":0,
                 "type":"",
                 "visible":true,
                 "width":12,
                 "x":1386.24,
                 "y":693.863
                }, 
                {
                 "gid":12,
                 "height":11,
                 "id":153,
                 "name":"",
                 "rotation":0,
                 "type":"",
                 "visible":true,
                 "width":12,
                 "x":1370.24,
                 "y":721.449
                }, 
                {
                 "gid":12,
                 "height":11,
                 "id":154,
                 "name":"",
                 "rotation":0,
                 "type":"",
                 "visible":true,
                 "width":12,
                 "x":1426.07,
                 "y":717.748
                }, 
                {
                 "gid":11,
                 "height":11,
                 "id":155,
                 "name":"",
                 "rotation":0,
                 "type":"",
                 "visible":true,
                 "width":12,
                 "x":1136,
                 "y":571.886
                }, 
                {
                 "gid":11,
                 "height":11,
                 "id":156,
                 "name":"",
                 "rotation":0,
                 "type":"",
                 "visible":true,
                 "width":12,
                 "x":989.24,
                 "y":574.345
                }, 
                {
                 "gid":9,
                 "height":20,
                 "id":157,
                 "name":"",
                 "rotation":0,
                 "type":"",
                 "visible":true,
                 "width":15,
                 "x":1073,
                 "y":540.886
                }, 
                {
                 "gid":9,
                 "height":20,
                 "id":161,
                 "name":"",
                 "rotation":0,
                 "type":"",
                 "visible":true,
                 "width":15,
                 "x":1097,
                 "y":495.886
                }, 
                {
                 "gid":9,
                 "height":20,
                 "id":162,
                 "name":"",
                 "rotation":0,
                 "type":"",
                 "visible":true,
                 "width":15,
                 "x":1160,
                 "y":490.886
                }, 
                {
                 "gid":9,
                 "height":20,
                 "id":163,
                 "name":"",
                 "rotation":0,
                 "type":"",
                 "visible":true,
                 "width":15,
                 "x":1191.04,
                 "y":499.138
                }, 
                {
                 "gid":9,
                 "height":20,
                 "id":164,
                 "name":"",
                 "rotation":0,
                 "type":"",
                 "visible":true,
                 "width":15,
                 "x":1142.48,
                 "y":506.311
                }, 
                {
                 "gid":9,
                 "height":20,
                 "id":165,
                 "name":"",
                 "rotation":0,
                 "type":"",
                 "visible":true,
                 "width":15,
                 "x":1133,
                 "y":539.886
                }, 
                {
                 "gid":9,
                 "height":20,
                 "id":166,
                 "name":"",
                 "rotation":0,
                 "type":"",
                 "visible":true,
                 "width":15,
                 "x":1245.1,
                 "y":487
                }, 
                {
                 "gid":9,
                 "height":20,
                 "id":167,
                 "name":"",
                 "rotation":0,
                 "type":"",
                 "visible":true,
                 "width":15,
                 "x":1280.42,
                 "y":489.759
                }, 
                {
                 "gid":9,
                 "height":20,
                 "id":168,
                 "name":"",
                 "rotation":0,
                 "type":"",
                 "visible":true,
                 "width":15,
                 "x":1237,
                 "y":533.886
                }, 
                {
                 "gid":9,
                 "height":20,
                 "id":169,
                 "name":"",
                 "rotation":0,
                 "type":"",
                 "visible":true,
                 "width":15,
                 "x":1288,
                 "y":536.886
                }, 
                {
                 "gid":9,
                 "height":20,
                 "id":170,
                 "name":"",
                 "rotation":0,
                 "type":"",
                 "visible":true,
                 "width":15,
                 "x":1298,
                 "y":777.886
                }, 
                {
                 "gid":9,
                 "height":20,
                 "id":171,
                 "name":"",
                 "rotation":0,
                 "type":"",
                 "visible":true,
                 "width":15,
                 "x":1339,
                 "y":780.886
                }, 
                {
                 "gid":11,
                 "height":11,
                 "id":241,
                 "name":"",
                 "rotation":0,
                 "type":"",
                 "visible":true,
                 "width":12,
                 "x":1106,
                 "y":666.886
                }, 
                {
                 "gid":12,
                 "height":11,
                 "id":242,
                 "name":"",
                 "rotation":0,
                 "type":"",
                 "visible":true,
                 "width":12,
                 "x":1075,
                 "y":782.886
                }],
         "opacity":1,
         "type":"objectgroup",
         "visible":true,
         "x":0,
         "y":0
        }, 
        {
         "draworder":"topdown",
         "id":4,
         "name":"resources",
         "objects":[
                {
                 "gid":20,
                 "height":101,
                 "id":257,
                 "name":"",
                 "rotation":0,
                 "type":"",
                 "visible":true,
                 "width":30,
                 "x":1171,
                 "y":622
                }, 
                {
                 "gid":20,
                 "height":101,
                 "id":258,
                 "name":"",
                 "rotation":0,
                 "type":"",
                 "visible":true,
                 "width":30,
                 "x":1225,
                 "y":623
                }, 
                {
                 "gid":20,
                 "height":101,
                 "id":259,
                 "name":"",
                 "rotation":0,
                 "type":"",
                 "visible":true,
                 "width":30,
                 "x":1200,
                 "y":666
                }, 
                {
                 "gid":19,
                 "height":79,
                 "id":260,
                 "name":"",
                 "rotation":0,
                 "type":"",
                 "visible":true,
                 "width":30,
                 "x":1251,
                 "y":662
                }, 
                {
                 "gid":18,
                 "height":99,
                 "id":261,
                 "name":"",
                 "rotation":0,
                 "type":"",
                 "visible":true,
                 "width":30,
                 "x":1309,
                 "y":663
                }, 
                {
                 "gid":31,
                 "height":91,
                 "id":262,
                 "name":"",
                 "rotation":0,
                 "type":"",
                 "visible":true,
                 "width":65,
                 "x":1128,
                 "y":706
                }, 
                {
                 "gid":32,
                 "height":91,
                 "id":263,
                 "name":"",
                 "rotation":0,
                 "type":"",
                 "visible":true,
                 "width":65,
                 "x":1102,
                 "y":744
                }, 
                {
                 "gid":34,
                 "height":91,
                 "id":264,
                 "name":"",
                 "rotation":0,
                 "type":"",
                 "visible":true,
                 "width":65,
                 "x":1048,
                 "y":744
                }, 
                {
                 "gid":34,
                 "height":91,
                 "id":265,
                 "name":"",
                 "rotation":0,
                 "type":"",
                 "visible":true,
                 "width":65,
                 "x":994,
                 "y":744
                }, 
                {
                 "gid":44,
                 "height":107,
                 "id":269,
                 "name":"",
                 "rotation":0,
                 "type":"",
                 "visible":true,
                 "width":27,
                 "x":1012,
                 "y":621
                }, 
                {
                 "gid":46,
                 "height":107,
                 "id":270,
                 "name":"",
                 "rotation":0,
                 "type":"",
                 "visible":true,
                 "width":27,
                 "x":959,
                 "y":623
                }, 
                {
                 "gid":40,
                 "height":107,
                 "id":271,
                 "name":"",
                 "rotation":0,
                 "type":"",
                 "visible":true,
                 "width":27,
                 "x":1039,
                 "y":506
                }, 
                {
                 "gid":38,
                 "height":107,
                 "id":272,
                 "name":"",
                 "rotation":0,
                 "type":"",
                 "visible":true,
                 "width":27,
                 "x":1012,
                 "y":545
                }, 
                {
                 "gid":26,
                 "height":101,
                 "id":273,
                 "name":"",
                 "rotation":0,
                 "type":"",
                 "visible":true,
                 "width":30,
                 "x":1252,
                 "y":584
                }, 
                {
                 "gid":24,
                 "height":99,
                 "id":274,
                 "name":"",
                 "rotation":0,
                 "type":"",
                 "visible":true,
                 "width":30,
                 "x":1090,
                 "y":581
                }, 
                {
                 "gid":35,
                 "height":33,
                 "id":275,
                 "name":"",
                 "rotation":0,
                 "type":"",
                 "visible":true,
                 "width":29,
                 "x":903,
                 "y":856
                }, 
                {
                 "gid":36,
                 "height":33,
                 "id":276,
                 "name":"",
                 "rotation":0,
                 "type":"",
                 "visible":true,
                 "width":29,
                 "x":927,
                 "y":895
                }, 
                {
                 "gid":36,
                 "height":33,
                 "id":277,
                 "name":"",
                 "rotation":0,
                 "type":"",
                 "visible":true,
                 "width":29,
                 "x":985,
                 "y":896
                }, 
                {
                 "gid":37,
                 "height":33,
                 "id":279,
                 "name":"",
                 "rotation":0,
                 "type":"",
                 "visible":true,
                 "width":29,
                 "x":878,
                 "y":817
                }, 
                {
                 "gid":31,
                 "height":91,
                 "id":280,
                 "name":"",
                 "rotation":0,
                 "type":"",
                 "visible":true,
                 "width":65,
                 "x":914,
                 "y":862
                }, 
                {
                 "gid":34,
                 "height":91,
                 "id":281,
                 "name":"",
                 "rotation":0,
                 "type":"",
                 "visible":true,
                 "width":65,
                 "x":940,
                 "y":900
                }, 
                {
                 "gid":39,
                 "height":87,
                 "id":283,
                 "name":"",
                 "rotation":0,
                 "type":"",
                 "visible":true,
                 "width":27,
                 "x":1337,
                 "y":936
                }, 
                {
                 "gid":40,
                 "height":107,
                 "id":285,
                 "name":"",
                 "rotation":0,
                 "type":"",
                 "visible":true,
                 "width":27,
                 "x":1308,
                 "y":894
                }, 
                {
                 "gid":38,
                 "height":107,
                 "id":286,
                 "name":"",
                 "rotation":0,
                 "type":"",
                 "visible":true,
                 "width":27,
                 "x":1343,
                 "y":861
                }, 
                {
                 "gid":38,
                 "height":107,
                 "id":287,
                 "name":"",
                 "rotation":0,
                 "type":"",
                 "visible":true,
                 "width":27,
                 "x":1280,
                 "y":854
                }, 
                {
                 "gid":39,
                 "height":87,
                 "id":288,
                 "name":"",
                 "rotation":0,
                 "type":"",
                 "visible":true,
                 "width":27,
                 "x":1312,
                 "y":817
                }, 
                {
                 "gid":44,
                 "height":107,
                 "id":289,
                 "name":"",
                 "rotation":0,
                 "type":"",
                 "visible":true,
                 "width":27,
                 "x":1233,
                 "y":853
                }, 
                {
                 "gid":46,
                 "height":107,
                 "id":290,
                 "name":"",
                 "rotation":0,
                 "type":"",
                 "visible":true,
                 "width":27,
                 "x":1231,
                 "y":775
                }, 
                {
                 "gid":23,
                 "height":101,
                 "id":291,
                 "name":"",
                 "rotation":0,
                 "type":"",
                 "visible":true,
                 "width":30,
                 "x":983,
                 "y":662
                }, 
                {
                 "gid":23,
                 "height":101,
                 "id":292,
                 "name":"",
                 "rotation":0,
                 "type":"",
                 "visible":true,
                 "width":30,
                 "x":848,
                 "y":937
                }, 
                {
                 "gid":23,
                 "height":101,
                 "id":293,
                 "name":"",
                 "rotation":0,
                 "type":"",
                 "visible":true,
                 "width":30,
                 "x":877,
                 "y":977
                }, 
                {
                 "gid":25,
                 "height":79,
                 "id":294,
                 "name":"",
                 "rotation":0,
                 "type":"",
                 "visible":true,
                 "width":30,
                 "x":903,
                 "y":932
                }, 
                {
                 "gid":25,
                 "height":79,
                 "id":295,
                 "name":"",
                 "rotation":0,
                 "type":"",
                 "visible":true,
                 "width":30,
                 "x":986,
                 "y":973
                }, 
                {
                 "gid":40,
                 "height":107,
                 "id":296,
                 "name":"",
                 "rotation":0,
                 "type":"",
                 "visible":true,
                 "width":27,
                 "x":984,
                 "y":1051
                }, 
                {
                 "gid":35,
                 "height":33,
                 "id":297,
                 "name":"",
                 "rotation":0,
                 "type":"",
                 "visible":true,
                 "width":29,
                 "x":1038,
                 "y":1042
                }, 
                {
                 "gid":35,
                 "height":33,
                 "id":298,
                 "name":"",
                 "rotation":0,
                 "type":"",
                 "visible":true,
                 "width":29,
                 "x":1084,
                 "y":1058
                }, 
                {
                 "gid":33,
                 "height":91,
                 "id":300,
                 "name":"",
                 "rotation":0,
                 "type":"",
                 "visible":true,
                 "width":65,
                 "x":912,
                 "y":705
                }, 
                {
                 "gid":33,
                 "height":91,
                 "id":301,
                 "name":"",
                 "rotation":0,
                 "type":"",
                 "visible":true,
                 "width":65,
                 "x":886,
                 "y":744
                }, 
                {
                 "gid":30,
                 "height":91,
                 "id":302,
                 "name":"",
                 "rotation":0,
                 "type":"",
                 "visible":true,
                 "width":65,
                 "x":1076,
                 "y":702
                }, 
                {
                 "gid":33,
                 "height":91,
                 "id":304,
                 "name":"",
                 "rotation":0,
                 "type":"",
                 "visible":true,
                 "width":65,
                 "x":1128,
                 "y":783
                }, 
                {
                 "gid":37,
                 "height":33,
                 "id":305,
                 "name":"",
                 "rotation":0,
                 "type":"",
                 "visible":true,
                 "width":29,
                 "x":930,
                 "y":504
                }, 
                {
                 "gid":33,
                 "height":91,
                 "id":306,
                 "name":"",
                 "rotation":0,
                 "type":"",
                 "visible":true,
                 "width":65,
                 "x":1075,
                 "y":1017
                }],
         "opacity":1,
         "properties":[
                {
                 "name":"grid_center",
                 "type":"bool",
                 "value":true
                }],
         "type":"objectgroup",
         "visible":true,
         "x":0,
         "y":0
        }],
 "nextlayerid":5,
 "nextobjectid":307,
 "orientation":"hexagonal",
 "renderorder":"left-down",
 "staggeraxis":"y",
 "staggerindex":"odd",
 "tiledversion":"1.2.5",
 "tileheight":55,
 "tilesets":[
        {
         "firstgid":1,
         "source":"..\/..\/hextest\/tiled\/maps\/hexes.tsx"
        }, 
        {
         "firstgid":9,
         "source":"..\/..\/hextest\/tiled\/maps\/decals.tsx"
        }, 
        {
         "firstgid":18,
         "source":"..\/..\/hextest\/tiled\/maps\/objects.tsx"
        }],
 "tilewidth":55,
 "type":"map",
 "version":1.2,
 "width":40
}